{
	"id": "1cd7f05c-3654-4cda-bcf3-061f18e4ae35",
	"name": "[Stage] Humansis",
	"values": [
		{
			"key": "base_url",
			"value": "stage.humansis.org",
			"enabled": true
		},
		{
			"key": "firewall",
			"value": "wsse",
			"enabled": true
		},
		{
			"key": "api",
			"value": "api",
			"enabled": true
		},
		{
			"key": "country",
			"value": "KHM",
			"enabled": true
		},
		{
			"key": "prefix",
			"value": "https://api",
			"enabled": true
		},
		{
			"key": "wsse_user",
			"value": "",
			"enabled": true
		},
		{
			"key": "wsse_password",
			"value": "",
			"enabled": true
		},
		{
			"key": "wsse_header",
			"value": "",
			"enabled": true
		},
		{
			"key": "wsse_salt",
			"value": "",
			"enabled": true
		},
		{
			"key": "wsse_salted_password",
			"value": "",
			"enabled": true
		}
	],
	"_postman_variable_scope": "environment",
	"_postman_exported_at": "2020-04-07T08:40:49.182Z",
	"_postman_exported_using": "Postman/7.21.1"
}